kesspy-0.2.0.dist-info/METADATA
kesspy-0.2.0.dist-info/WHEEL
kesspy/__init__.py
kesspy/kesspy.cpython-311-x86_64-linux-gnu.so
kesspy-0.2.0.dist-info/RECORD
