Metadata-Version: 2.1
Name: kesspy
Version: 0.2.0
